pyanimate/__init__.py
pyanimate/array.py
pyanimate/compose.py
pyanimate/geom.py
pyanimate/graph.py
pyanimate/image.py
pyanimate/tween.py
pyanimate-0.1.dist-info/METADATA
pyanimate-0.1.dist-info/RECORD
pyanimate-0.1.dist-info/WHEEL
pyanimate-0.1.dist-info/top_level.txt
