Metadata-Version: 2.1
Name: pyanimate
Version: 0.1
Summary: Create animated gifs, movies and images in Python
Home-page: https://github.com/martinmcbride/pyanimate
Author: Martin McBride
Author-email: mcbride.martin@gmail.com
License: MIT
Platform: UNKNOWN
Classifier: Programming Language :: Python :: 3
Classifier: License :: OSI Approved :: MIT License
Classifier: Operating System :: OS Independent
